{"_default": {"1": {"isbn": "49837410934324", "title": "The Clean Coder", "author": "ThatGuy", "state": "finished", "type": "by_chapter", "page_count": 456, "chapter_number": 0, "current_chapter": 0, "current_page": 0, "channel_id": "78910", "object_type": "book"}, "2": {"isbn": "9780140328721", "title": "Clean Code", "author": "ThatGuy", "state": "finished", "type": "by_page", "page_count": 123, "chapter_number": 0, "current_chapter": 0, "current_page": 0, "channel_id": "123456", "object_type": "book"}, "9": {"isbn": "9780132350884", "title": "Clean Code", "author": "Robert C. Martin", "page_count": 464, "state": "on_going", "type": "by_page", "chapter_number": 0, "current_chapter": 0, "current_page": 0, "channel_id": "C09E9HFL4C9", "object_type": "book"}, "10": {"name": "Docker", "channel_id": "C09HG93TZGV", "object_type": "tech"}, "11": {"isbn": "9782266343992", "title": "Hunger Games - Int\u00e9grale", "author": "Suzanne Collins", "page_count": 1246, "state": "on_going", "type": "by_page", "chapter_number": 0, "current_chapter": 0, "current_page": 83, "channel_id": "C09HZ72LBKK", "object_type": "book"}, "12": {"name": "Alembic", "channel_id": "C09H4C6B70F", "object_type": "tech"}, "13": {"name": "SQLAlchemy", "object_type": "tech", "channel_id": "123456"}, "14": {"name": "Python", "object_type": "tech", "channel_id": "7891011"}, "15": {"name": "Go", "object_type": "tech", "channel_id": "123456"}, "16": {"isbn": "9780136083252", "title": "Clean Code", "author": "Robert C. Martin", "page_count": 464, "state": "on_going", "type": "by_page", "chapter_number": 0, "current_chapter": 0, "current_page": 0, "channel_id": "C09E9HFL4C9", "object_type": "book"}}}